liv/__init__.py
liv/train_liv.py
liv/trainer.py
liv/models/__init__.py
liv/models/model_liv.py
liv/models/clip/__init__.py
liv/models/clip/clip/__init__.py
liv/models/clip/clip/bpe_simple_vocab_16e6.txt.gz
liv/models/clip/clip/clip.py
liv/models/clip/clip/model.py
liv/models/clip/clip/simple_tokenizer.py
liv/utils/__init__.py
liv/utils/data_loaders.py
liv/utils/logger.py
liv/utils/plotter.py
liv/utils/utils.py
LIV_robotics-0.1.5.dist-info/LICENSE
LIV_robotics-0.1.5.dist-info/METADATA
LIV_robotics-0.1.5.dist-info/WHEEL
LIV_robotics-0.1.5.dist-info/top_level.txt
LIV_robotics-0.1.5.dist-info/RECORD
