Metadata-Version: 2.1
Name: LIV-robotics
Version: 0.1.5
Summary: LIV: Language-Image Representations and Rewards for Robotic Control
Author: Jason Ma
Author-email: Jason Ma <jasonyma@seas.upenn.edu>
Project-URL: Homepage, https://github.com/penn-pal-lab/LIV
Project-URL: Bug Tracker, https://github.com/penn-pal-lab/LIV/issues
Classifier: Programming Language :: Python :: 3
Classifier: License :: OSI Approved :: MIT License
Classifier: Operating System :: OS Independent
Requires-Python: >=3.7
License-File: LICENSE
Requires-Dist: torch
Requires-Dist: torchvision >=0.8.2
Requires-Dist: omegaconf ==2.1.1
Requires-Dist: hydra-core ==1.1.1
Requires-Dist: pillow ==9.5.0
Requires-Dist: opencv-python
Requires-Dist: matplotlib
Requires-Dist: flatten-dict
Requires-Dist: gdown
Requires-Dist: huggingface-hub
Requires-Dist: tabulate
Requires-Dist: pandas
Requires-Dist: scipy
Requires-Dist: scikit-learn
Requires-Dist: scikit-video
Requires-Dist: transforms3d
Requires-Dist: moviepy
Requires-Dist: termcolor
Requires-Dist: ftfy
Requires-Dist: regex
Requires-Dist: tqdm
